we_test/__init__.py
we_test/setup.py
we_testtttt/__init__.py
we_testtttt/setup.py
we_testtttt-0.1.9.dist-info/LICENSE
we_testtttt-0.1.9.dist-info/METADATA
we_testtttt-0.1.9.dist-info/WHEEL
we_testtttt-0.1.9.dist-info/top_level.txt
we_testtttt-0.1.9.dist-info/RECORD
