Metadata-Version: 2.1
Name: we-testtttt
Version: 0.1.9
Summary: Wealth Engine ReportData Generator
Home-page: http://192.168.1.7:10600/xiazeyu/we_report.git
Author: Xia Zeyu
Author-email: xiazeyu@wealthengine.cn
License: UNKNOWN
Platform: UNKNOWN
Classifier: Programming Language :: Python :: 3
Classifier: License :: OSI Approved :: MIT License
Classifier: Operating System :: OS Independent
License-File: LICENSE
Requires-Dist: numpy (>=1.15)
Requires-Dist: pandas (>=1.0.3)
Requires-Dist: arrow (>=0.17.0)
Requires-Dist: sqlalchemy (>=1.3.18)
Requires-Dist: scikit-learn
Requires-Dist: matplotlib
Requires-Dist: xlsxwriter
Requires-Dist: scipy
Requires-Dist: statsmodels
Requires-Dist: six
